xvalidator/__init__.py
xvalidator/nationalcode.py
xvalidator-1.0.1.dist-info/METADATA
xvalidator-1.0.1.dist-info/WHEEL
xvalidator-1.0.1.dist-info/RECORD
